LICENSE.txt
MANIFEST.in
README.md
setup.py
tkcomponents/__init__.py
tkcomponents/component.py
tkcomponents.egg-info/PKG-INFO
tkcomponents.egg-info/SOURCES.txt
tkcomponents.egg-info/dependency_links.txt
tkcomponents.egg-info/requires.txt
tkcomponents.egg-info/top_level.txt
tkcomponents/basiccomponents/__init__.py
tkcomponents/basiccomponents/alert.py
tkcomponents/basiccomponents/buttonlistbox.py
tkcomponents/basiccomponents/constants.py
tkcomponents/basiccomponents/datestepper.py
tkcomponents/basiccomponents/labelwrapper.py
tkcomponents/basiccomponents/progressbar.py
tkcomponents/basiccomponents/stepper.py
tkcomponents/basiccomponents/steppertable.py
tkcomponents/basiccomponents/stringeditor.py
tkcomponents/basiccomponents/textcarousel.py
tkcomponents/basiccomponents/timedframe.py
tkcomponents/basiccomponents/timercontrol.py
tkcomponents/basiccomponents/togglebutton.py
tkcomponents/basiccomponents/verticalscrollframe.py
tkcomponents/basiccomponents/classes/dateticker.py
tkcomponents/basiccomponents/classes/timer.py
tkcomponents/extensions/__init__.py
tkcomponents/extensions/draganddrop.py
tkcomponents/extensions/gridhelper.py