Metadata-Version: 2.1
Name: tkcomponents
Version: 4.0.0
Summary: An OOP framework for Tkinter, inspired by React
Home-page: https://github.com/immijimmi/tkcomponents
Download-URL: https://github.com/immijimmi/tkcomponents/archive/refs/tags/v4.0.0.tar.gz
Author: immijimmi
Author-email: immijimmi1@gmail.com
License: MIT
Keywords: ui,gui,graphical,user,interface
Classifier: Development Status :: 4 - Beta
Classifier: Intended Audience :: Developers
Classifier: Topic :: Software Development :: Libraries :: Application Frameworks
Classifier: License :: OSI Approved :: MIT License
Classifier: Programming Language :: Python :: 3.11
License-File: LICENSE.txt
